streamlit_app/__init__.py
streamlit_app/app.py
streamlit_app/handle_transformation.py
streamlit_app/launcher.py
streamlit_app/metadata_topology.py
streamlit_app/process.py
Informatica_Migration_Bilvantis_StreamlitApp-0.1.dist-info/METADATA
Informatica_Migration_Bilvantis_StreamlitApp-0.1.dist-info/WHEEL
Informatica_Migration_Bilvantis_StreamlitApp-0.1.dist-info/entry_points.txt
Informatica_Migration_Bilvantis_StreamlitApp-0.1.dist-info/top_level.txt
Informatica_Migration_Bilvantis_StreamlitApp-0.1.dist-info/RECORD
